dms/__init__.py
dms/app.py
dms/cli.py
dms/db.py
dms/ds.py
dms/errors.py
dms/form.py
dms/logger.py
dms/messages.py
dms/middlewares.py
dms/orm.py
dms/router.py
dms/schema.py
dms/settings.py
dms/state.py
dms/template.py
dms/utils.py
dms/views.py
dms/templates/default/404.jinja
dms/templates/default/500.jinja
dms/templates/default/base.jinja
dms/templates/default/index.jinja
dms/templates/default/login.jinja
dms/templates/default/model.jinja
dms/templates/default/models.jinja
dms/templates/default/scripts.js
dms/templates/default/styles.css
tests/dms/__init__.py
tests/dms/test_orm.py
tests/dms/test_state.py
dms-0.0.3.dist-info/METADATA
dms-0.0.3.dist-info/WHEEL
dms-0.0.3.dist-info/entry_points.txt
dms-0.0.3.dist-info/license
dms-0.0.3.dist-info/top_level.txt
dms-0.0.3.dist-info/RECORD
