Metadata-Version: 2.1
Name: dms
Version: 0.0.3
Summary: database management service dashboard
Home-page: https://github.com/ambrozic/dms
Author: ambrozic
Author-email: ambrozic@gmail.com
Maintainer: ambrozic
Maintainer-email: ambrozic@gmail.com
License: BSD
Project-URL: Code, https://github.com/ambrozic/dms
Project-URL: Documentation, https://ambrozic.github.io/dms
Keywords: database management service dashboard admin
Platform: UNKNOWN
Classifier: Programming Language :: Python
Classifier: Environment :: Web Environment
Classifier: Operating System :: MacOS :: MacOS X
Classifier: Operating System :: POSIX
Classifier: License :: OSI Approved :: BSD License
Classifier: Programming Language :: Python :: 3
Classifier: Programming Language :: Python :: 3.7
Classifier: Topic :: Internet
Classifier: Topic :: Software Development :: Libraries :: Python Modules
Classifier: Intended Audience :: Developers
Requires-Python: >=3.7
Requires-Dist: databases (==0.2.6)
Requires-Dist: itsdangerous (==1.1.0)
Requires-Dist: jinja2 (==2.10.3)
Requires-Dist: passlib (==1.7.2)
Requires-Dist: python-multipart (==0.0.5)
Requires-Dist: sqlalchemy (==1.3.12)
Requires-Dist: starlette (==0.13.0)
Requires-Dist: uvicorn (==0.11.1)
Provides-Extra: docs
Requires-Dist: mkdocs-material (==4.4.3) ; extra == 'docs'
Requires-Dist: mkdocs (==1.0.4) ; extra == 'docs'
Requires-Dist: pygments (==2.5.2) ; extra == 'docs'
Requires-Dist: pymdown-extensions (==6.1) ; extra == 'docs'
Provides-Extra: postgresql
Requires-Dist: asyncpg (==0.20.0) ; extra == 'postgresql'
Requires-Dist: psycopg2-binary (==2.8.4) ; extra == 'postgresql'
Provides-Extra: sqlite
Requires-Dist: aiosqlite (==0.11.0) ; extra == 'sqlite'
Provides-Extra: tests
Requires-Dist: black (==19.10b0) ; extra == 'tests'
Requires-Dist: codecov (<3.0,>=2.0) ; extra == 'tests'
Requires-Dist: isort (<5.0,>4.0) ; extra == 'tests'
Requires-Dist: pipdeptree (<1.0,>=0.13) ; extra == 'tests'
Requires-Dist: pytest-asyncio (==0.10.0) ; extra == 'tests'
Requires-Dist: pytest-cov (<3.0,>=2.7) ; extra == 'tests'
Requires-Dist: pytest (<6.0,>=5.0) ; extra == 'tests'
Requires-Dist: sqlalchemy-utils (==0.36.1) ; extra == 'tests'
